MANIFEST.in
README.rst
setup.cfg
setup.py
phonetic/__init__.py
phonetic/data.txt
phonetic/phonetic.py
phonetic/text.txt
phonetic.egg-info/PKG-INFO
phonetic.egg-info/SOURCES.txt
phonetic.egg-info/dependency_links.txt
phonetic.egg-info/requires.txt
phonetic.egg-info/top_level.txt