Metadata-Version: 1.1
Name: phonetic
Version: 0.0.3
Summary: A simple Cantonese phonetic tools
Home-page: https://github.com/kk17/phonetic
Author: kk17
Author-email: zk.chan007@gmail.com
License: MIT
Keywords: cantonese phonetic notation 粤语 注音
Platform: UNKNOWN
Classifier: Development Status :: 3 - Alpha
Classifier: Intended Audience :: Developers
Classifier: Topic :: Software Development :: Build Tools
Classifier: License :: OSI Approved :: MIT License
Classifier: Programming Language :: Python :: 2
Classifier: Programming Language :: Python :: 2.6
Classifier: Programming Language :: Python :: 2.7
